rex_xai/__init__.py
rex_xai/explanation/evaluation.py
rex_xai/explanation/explanation.py
rex_xai/explanation/multi_explanation.py
rex_xai/explanation/rex.py
rex_xai/input/config.py
rex_xai/input/input_data.py
rex_xai/input/onnx.py
rex_xai/lib.py
rex_xai/mutants/box.py
rex_xai/mutants/distributions.py
rex_xai/mutants/mutant.py
rex_xai/mutants/occlusions.py
rex_xai/output/database.py
rex_xai/output/visualisation.py
rex_xai/responsibility/prediction.py
rex_xai/responsibility/resp_maps.py
rex_xai/responsibility/responsibility.py
rex_xai/rex_wrapper.py
rex_xai/utils/_utils.py
rex_xai/utils/logger.py
rex_xai-0.4.0.dist-info/LICENSE
rex_xai-0.4.0.dist-info/METADATA
rex_xai-0.4.0.dist-info/WHEEL
rex_xai-0.4.0.dist-info/entry_points.txt
rex_xai-0.4.0.dist-info/RECORD
