Metadata-Version: 2.3
Name: rex-xai
Version: 0.4.0
Summary: causal Responsibility-based eXplanations of black-box-classifiers
Author: David Kelly
Author-email: dkellino@gmail.com
Requires-Python: >=3.10
Classifier: Programming Language :: Python :: 3
Classifier: Programming Language :: Python :: 3.10
Classifier: Programming Language :: Python :: 3.11
Classifier: Programming Language :: Python :: 3.12
Classifier: Programming Language :: Python :: 3.13
Provides-Extra: 3d
Requires-Dist: anytree (>=2.8.0)
Requires-Dist: dash (>=2.1.0) ; extra == "3d"
Requires-Dist: fastcache (>=1.1.0)
Requires-Dist: imutils (>=0.5.4)
Requires-Dist: kaleido (==0.2.1) ; extra == "3d"
Requires-Dist: matplotlib (>=3.7.1)
Requires-Dist: nibabel (>=5.2.1) ; extra == "3d"
Requires-Dist: numpy (==1.26.4)
Requires-Dist: onnxruntime (>=1.18.0)
Requires-Dist: pandas (>=2.2.0)
Requires-Dist: pillow (>=10.3.0)
Requires-Dist: plotly (>=5.4.0) ; extra == "3d"
Requires-Dist: scikit-image (>=0.21.0)
Requires-Dist: scipy (>=1.10)
Requires-Dist: sqlalchemy (>=2.0.16)
Requires-Dist: tabulate (>=0.9.0)
Requires-Dist: toml (>=0.10)
Requires-Dist: torch (>=2.6.0)
Requires-Dist: tqdm (>=4.65.0)
Project-URL: Bug Tracker, https://github.com/ReX-XAI/ReX/issues
Project-URL: Documentation, https://rex-xai.readthedocs.io/
Project-URL: Homepage, https://rex-xai.readthedocs.io//
Project-URL: Repository, https://github.com/ReX-XAI/ReX
